LICENSE
MANIFEST.in
README.md
pyproject.toml
requirements.txt
setup.cfg
setup.py
custom_diffusion/__init__.py
custom_diffusion/demo.py
custom_diffusion/preprocces.py
custom_diffusion.egg-info/PKG-INFO
custom_diffusion.egg-info/SOURCES.txt
custom_diffusion.egg-info/dependency_links.txt
custom_diffusion.egg-info/requires.txt
custom_diffusion.egg-info/top_level.txt
custom_diffusion/pipelines/__init__.py
custom_diffusion/pipelines/controlnet_img2img.py
custom_diffusion/pipelines/controlnet_inpaint.py
custom_diffusion/pipelines/controlnet_pipeline.py
custom_diffusion/pipelines/stable_diffusion_img2img.py
custom_diffusion/pipelines/stable_diffusion_instruct_pix2pix.py
custom_diffusion/pipelines/stable_diffusion_text2image.py
custom_diffusion/pipelines/stable_diffusion_upscale.py
custom_diffusion/utils/__init__.py
custom_diffusion/utils/data_utils.py
custom_diffusion/utils/downloads.py
custom_diffusion/utils/model_list.py
custom_diffusion/utils/scheduler_utils.py
custom_diffusion/utils/video_utils.py